int_encoder/__init__.py
int_encoder/config.py
int_encoder-1.0.0.dist-info/LICENSE
int_encoder-1.0.0.dist-info/METADATA
int_encoder-1.0.0.dist-info/WHEEL
int_encoder-1.0.0.dist-info/top_level.txt
int_encoder-1.0.0.dist-info/RECORD
