Metadata-Version: 2.1
Name: int_encoder
Version: 1.0.0
Summary: A library for encoding and decoding integers using modular arithmetic
Author: Int Encoder
License: MIT
Project-URL: Repository, https://github.com/intencoder/int_encoder
Keywords: integer,encoding,modular arithmetic,decoding,encryption
Classifier: Development Status :: 5 - Production/Stable
Classifier: Intended Audience :: Developers
Classifier: License :: OSI Approved :: MIT License
Classifier: Programming Language :: Python :: 3
Classifier: Programming Language :: Python :: 3.8
Classifier: Programming Language :: Python :: 3.9
Classifier: Programming Language :: Python :: 3.10
Classifier: Programming Language :: Python :: 3.11
Classifier: Operating System :: OS Independent
License-File: LICENSE
